LICENSE
MANIFEST.in
README.md
setup.py
sniptool/__init__.py
sniptool/__main__.py
sniptool/config.py
sniptool.egg-info/PKG-INFO
sniptool.egg-info/SOURCES.txt
sniptool.egg-info/dependency_links.txt
sniptool.egg-info/entry_points.txt
sniptool.egg-info/not-zip-safe
sniptool.egg-info/requires.txt
sniptool.egg-info/top_level.txt