Metadata-Version: 1.1
Name: sniptool
Version: 0.5
Summary: Code snippet management tool
Home-page: https://github.com/rcook/sniptool
Author: Richard Cook
Author-email: rcook@rcook.org
License: MIT
Platform: UNKNOWN
Classifier: Development Status :: 3 - Alpha
Classifier: License :: OSI Approved :: MIT License
Classifier: Programming Language :: Python :: 2.7
